{
  "tierSponsors": [
    {
      "tier": [
        {
          "value": "tier-cYGYq5-ae",
          "label": "Top-Tier"
        }
      ],
      "sponsors": [
        {
          "marquee": "Your text here! (150-characters max)",
          "sponsorColor": "#414042",
          "logo": "/img/tier1-default-sponsor-logo.png",
          "name": "Top-Tier",
          "intro": "Sponsor Description (1000-character max) Lorem ipsum dolor sit amet, consectetur adipiscing elit. Phasellus eget ipsum tempor lorem interdum volutpat eu et elit. Sed eleifend justo et semper ultrices. Fusce porta ut sapien at posuere. Donec placerat, lacus eget imperdiet maximus, nunc lectus viverra ligula, in sodales tortor justo vel sem. Vestibulum eleifend, nibh a dapibus rhoncus, tortor dui venenatis enim, ac euismod augue velit at justo. Cras porta lacus est, nec rhoncus augue luctus quis. Pellentesque justo risus, scelerisque laoreet tortor quis, TOP TIER TEXT.",
          "headerImage": "/img/tier1-default-sponsor-headerimage-toptier.png",
          "socialNetworks": [],
          "sponsorId": 24,
          "title": "Top-Tier Sponsor Test ",
          "companyId": 22,
          "documents": {
            "links": [
              {
                "class_name": "PresentationLink",
                "name": "Your social media links here ",
                "order": 1,
                "link": "https://www.facebook.com/FNTECH"
              }
            ],
            "videos": [
              {
                "class_name": "PresentationVideo",
                "name": "Your external video links here ",
                "order": 2,
                "link": "https://www.youtube.com/channel/UC81WrqqnYmigub0fTNKT-Mw"
              }
            ]
          },
          "columnAds": [
            {
              "image": "/img/tier1-default-sponsor-space1.png",
              "link": "fntech.com"
            }
          ],
          "id": 24,
          "email": "support@fntech.com",
          "usesSponsorPage": true
        },
        {
          "marquee": "Your event one-stop-shop, no matter the scope or size. Production + Event Management + Creative. We have you covered. ",
          "sponsorColor": "#0C64C8",
          "logo": "/img/logo-top-tier-fntech.png",
          "name": "FNTECH",
          "intro": "**WE SPEAK EVENTS: In-person, virtual, and everything in-between.**\\\nOver the past 20+ years, we’ve successfully partnered with top-tier companies like Apple, Facebook, Wells Fargo, Vans, and Volcom on events of all sizes, types and budgets. Domestic and abroad. Intimate and straightforward to extremely complex and expansive. We have two large headquarters—one in the Northern California Bay Area and another in Southern California, which includes a virtual reality lab, 3D printing hub, and robust wood/metal fabrication shop. We’re a people-first company, which to us means treating every employee, client, vendor, partner, and community member with honesty, integrity, and respect. It’s part of our corporate ethos. People power our mission and we are eternally grateful to know and work with some of the best in the business. And as always, we make sure to have a lot of fun along the way. For more FNinfo, visit us at [fntech.com](http://fntech.com/).",
          "headerVideo": "https://fntech.sfo2.cdn.digitaloceanspaces.com/Yoco/FNTECH%20animated%20logo_Black_012021.mp4",
          "advertiseImage": "",
          "sponsorId": 44,
          "title": "",
          "companyId": 4,
          "columnAds": [],
          "id": 44,
          "email": "info@fntech.com",
          "usesSponsorPage": true
        }
      ]
    },
    {
      "tier": [
        {
          "value": "tier-DHcI3dWGk",
          "label": "Mid-Tier"
        }
      ],
      "sponsors": [
        {
          "marquee": "Your text here! (150-characters max)",
          "sideImage": "",
          "externalLink": "",
          "sponsorColor": "#58595b",
          "logo": "/img/tier1-default-sponsor-logo.png",
          "name": "Mid-Tier",
          "intro": "Sponsor Description (1000-character max) Lorem ipsum dolor sit amet, consectetur adipiscing elit. Phasellus eget ipsum tempor lorem interdum volutpat eu et elit. Sed eleifend justo et semper ultrices. Fusce porta ut sapien at posuere. Donec placerat, lacus eget imperdiet maximus, nunc lectus viverra ligula, in sodales tortor justo vel sem. Vestibulum eleifend, nibh a dapibus rhoncus, tortor dui venenatis enim, ac euismod augue velit at justo. Cras porta lacus est, nec rhoncus augue luctus quis. Pellentesque justo risus, scelerisque laoreet tortor quis, Test Text",
          "headerVideo": "",
          "headerImage": "/img/tier1-default-sponsor-headerimage-middletier.png",
          "socialNetworks": [],
          "chatLink": "",
          "sponsorId": 25,
          "title": "Mid-Tier Sponsor",
          "companyId": 23,
          "documents": {
            "slides": [],
            "links": [
              {
                "class_name": "PresentationLink",
                "name": "Your social media links here ",
                "order": 1,
                "link": "https://www.facebook.com/FNTECH"
              }
            ],
            "videos": [
              {
                "class_name": "PresentationVideo",
                "name": "Your external video links here ",
                "link": "https://www.youtube.com/channel/UC81WrqqnYmigub0fTNKT-Mw",
                "order": 2
              }
            ]
          },
          "columnAds": [
            {
              "image": "/img/tier1-default-sponsor-space1.png",
              "button": "",
              "link": "https://fntech.com"
            }
          ],
          "id": 25,
          "email": "support@fntech.com",
          "usesSponsorPage": true
        }
      ]
    },
    {
      "tier": [
        {
          "value": "tier-U_wEwGX8a",
          "label": "Lower-Tier"
        }
      ],
      "sponsors": [
        {
          "marquee": "Your text here! (150-characters max)",
          "sideImage": "/img/tier1-default-sponsor-sideimage.png",
          "externalLink": "",
          "sponsorColor": "#6d6e71",
          "logo": "/img/tier1-default-sponsor-logo.png",
          "name": "Lower-Tier",
          "intro": "Sponsor Description (1000-character max) Lorem ipsum dolor sit amet, consectetur adipiscing elit. Phasellus eget ipsum tempor lorem interdum volutpat eu et elit. Sed eleifend justo et semper ultrices. Fusce porta ut sapien at posuere. Donec placerat, lacus eget imperdiet maximus, nunc lectus viverra ligula, in sodales tortor justo vel sem. Vestibulum eleifend, nibh a dapibus rhoncus, tortor dui venenatis enim, ac euismod augue velit at justo. Cras porta lacus est, nec rhoncus augue luctus quis. Pellentesque justo risus, scelerisque laoreet tortor quis, vehicula volutpat ipsum.",
          "headerVideo": "",
          "headerImage": "/img/tier1-default-sponsor-headerimage-lowertier.png",
          "socialNetworks": [],
          "chatLink": "",
          "sponsorId": 26,
          "title": "Lower-Tier Sponsor",
          "companyId": 24,
          "documents": {
            "slides": [],
            "links": [
              {
                "class_name": "PresentationLink",
                "name": "Your social media links here ",
                "link": "https://www.facebook.com/FNTECH",
                "order": 1
              }
            ],
            "videos": [
              {
                "class_name": "PresentationVideo",
                "link": "https://www.youtube.com/channel/UC81WrqqnYmigub0fTNKT-Mw",
                "order": 2,
                "name": "Your external video links here "
              }
            ]
          },
          "columnAds": [
            {
              "image": "/img/tier1-default-sponsor-space1.png",
              "button": "",
              "link": "https://www.fntech.com"
            }
          ],
          "id": 26,
          "email": "support@fntech.com",
          "usesSponsorPage": true
        }
      ]
    }
  ]
}